gasprice.py
gasprice-1.2.0.dist-info/entry_points.txt
gasprice-1.2.0.dist-info/WHEEL
gasprice-1.2.0.dist-info/METADATA
gasprice-1.2.0.dist-info/RECORD
