Metadata-Version: 2.1
Name: gasprice
Version: 1.2.0
Summary: predict ethereum gas price
Home-page: https://github.com/banteg/gasprice
License: MIT
Author: banteg
Author-email: banteeg@gmail.com
Requires-Python: >=3.6,<4.0
Classifier: License :: OSI Approved :: MIT License
Classifier: Programming Language :: Python :: 3
Classifier: Programming Language :: Python :: 3.6
Classifier: Programming Language :: Python :: 3.7
Requires-Dist: click (>=7.0,<8.0)
Requires-Dist: pandas (>=0.24.2,<0.25.0)
Requires-Dist: retry (>=0.9.2,<0.10.0)
Requires-Dist: sanic (>=19.3,<20.0)
Requires-Dist: web3 (>=4.9,<5.0)
Project-URL: Repository, https://github.com/banteg/gasprice
